backupper/__init__.py
backupper/backupper.py
backupper_lf23-1.1.0.dist-info/LICENSE
backupper_lf23-1.1.0.dist-info/METADATA
backupper_lf23-1.1.0.dist-info/WHEEL
backupper_lf23-1.1.0.dist-info/entry_points.txt
backupper_lf23-1.1.0.dist-info/top_level.txt
backupper_lf23-1.1.0.dist-info/RECORD
