Metadata-Version: 2.1
Name: backupper-lf23
Version: 1.1.0
Summary: Un semplice Python script per gestire i backups
Home-page: https://github.com/lucaf23/backupper
Author: Luca Ferrari
Author-email: luca10.ferrari@edu.unife.it
License: MIT
Classifier: Programming Language :: Python :: 3
Classifier: License :: OSI Approved :: MIT License
Classifier: Operating System :: OS Independent
Requires-Python: >=3.6
License-File: LICENSE
Requires-Dist: pyzipper
